migrations/0001_initial.py
migrations/0002_auto_20201123_1111.py
migrations/0003_oauthuser_groups.py
migrations/0004_oauthuser_user_permissions.py
migrations/__init__.py
sso_auth/__init__.py
sso_auth/admin.py
sso_auth/apps.py
sso_auth/backends.py
sso_auth/middleware.py
sso_auth/models.py
sso_auth/tests.py
sso_auth/urls.py
sso_auth/views.py
sso_auth/services/__init__.py
sso_auth/services/get_token_by_refresh.py
sso_auth/services/get_user_info.py
sso_auth/static/__init__.py
sso_auth/static/style.css
sso_auth/templates/__init__.py
sso_auth/templates/success_auth.html
ksu_sso_auth-0.1.6.dist-info/LICENSE
ksu_sso_auth-0.1.6.dist-info/METADATA
ksu_sso_auth-0.1.6.dist-info/WHEEL
ksu_sso_auth-0.1.6.dist-info/top_level.txt
ksu_sso_auth-0.1.6.dist-info/RECORD
