Metadata-Version: 2.1
Name: ksu-sso-auth
Version: 0.1.6
Summary: Module for use ksu sso service 
Home-page: https://gitlab.com/shoytov/sso_auth
Author: Dmitry Shoytov
Author-email: shoytov@gmail.com
License: UNKNOWN
Platform: UNKNOWN
Classifier: Programming Language :: Python :: 3
Classifier: License :: OSI Approved :: MIT License
Classifier: Operating System :: OS Independent
Requires-Python: >=3.6
Requires-Dist: requests
